pywhu3d/__init__.py
pywhu3d/evaluation.py
pywhu3d/tool.py
pywhu3d/configs/__init__.py
pywhu3d/configs/als_config.py
pywhu3d/configs/base_config.py
pywhu3d/configs/mls_config.py
pywhu3d/configs/mls_config_pole.py
pywhu3d/configs/mls_w_config.py
pywhu3d/configs/paris_config.py
pywhu3d/configs/s3dis_config.py
pywhu3d/configs/scannet_config.py
pywhu3d/configs/toronto_config.py
pywhu3d/configs/wrap_configs.py
pywhu3d-0.2.17.dist-info/LICENSE
pywhu3d-0.2.17.dist-info/METADATA
pywhu3d-0.2.17.dist-info/WHEEL
pywhu3d-0.2.17.dist-info/top_level.txt
pywhu3d-0.2.17.dist-info/RECORD
