Metadata-Version: 2.1
Name: pywhu3d
Version: 0.2.17
Summary: Example pywhu3d tool Package
Home-page: https://github.com/astroy
Author: Xu Han
Author-email: hanxu@glad3d.com
Keywords: whu3d,dataset,package
Classifier: Development Status :: 5 - Production/Stable
Classifier: Intended Audience :: Developers
Classifier: Topic :: Software Development :: Build Tools
Classifier: Programming Language :: Python :: 3
Classifier: Programming Language :: Python :: 3.6
Classifier: Programming Language :: Python :: 3.7
Classifier: Programming Language :: Python :: 3.8
Classifier: Programming Language :: Python :: 3.9
Classifier: Programming Language :: Python :: 3 :: Only
Classifier: License :: OSI Approved :: MIT License
Classifier: Operating System :: OS Independent
Requires-Python: >=3.6
License-File: LICENSE
Requires-Dist: numpy>=1.21.6
Requires-Dist: h5py>=3.7.0
Requires-Dist: laspy>=2.1.0
Requires-Dist: open3d>=0.9.0
Requires-Dist: plyfile>=0.7.4
Requires-Dist: rich>=10.12.0
Requires-Dist: prettytable
Requires-Dist: xlwt
Requires-Dist: scipy
Provides-Extra: dev
Requires-Dist: check-manifest; extra == "dev"
